{
  "schema_version": "curriculum-command-coverage.v1",
  "authoritative_catalog": "data/generated/learning-command-catalog.json",
  "authoritative_command_count": 163,
  "commands_mapped": 163,
  "commands_omitted": [],
  "extra_learning_records": [],
  "vendors_represented": [
    "aruba_cx",
    "cisco_ios",
    "hp_comware",
    "linux",
    "windows_cmd"
  ],
  "total_curriculum_phases": 10,
  "total_curriculum_levels": 40,
  "fully_authored_levels": [
    "level_00"
  ],
  "planned_levels": [
    "level_01",
    "level_02",
    "level_03",
    "level_04",
    "level_05",
    "level_06",
    "level_07",
    "level_08",
    "level_09",
    "level_10",
    "level_11",
    "level_12",
    "level_13",
    "level_14",
    "level_15",
    "level_16",
    "level_17",
    "level_18",
    "level_19",
    "level_20",
    "level_21",
    "level_22",
    "level_23",
    "level_24",
    "level_25",
    "level_26",
    "level_27",
    "level_28",
    "level_29",
    "level_30",
    "level_31",
    "level_32",
    "level_33",
    "level_34",
    "level_35",
    "level_36",
    "level_37",
    "level_38",
    "level_39"
  ],
  "specialization_paths": [
    "access-switching-technician",
    "campus-network-support",
    "multi-vendor-switching",
    "windows-linux-network-diagnostics",
    "wireless-and-edge-support",
    "security-and-change-control",
    "datacenter-operations",
    "automation-and-documentation"
  ],
  "alias_policy": "Aliases and abbreviations share the same canonical learning identity.",
  "honest_coverage_policy": "No planned level is marked complete, verified, or practically mastered without evidence.",
  "passed": true
}
